collective.webhook-0.3.0-py2.7-nspkg.pth
collective/webhook/__init__.py
collective/webhook/configure.zcml
collective/webhook/testing.py
collective/webhook/utils.py
collective/webhook/actions/__init__.py
collective/webhook/actions/configure.zcml
collective/webhook/actions/webhook.py
collective/webhook/actions/templates/webhook.pt
collective/webhook/actions/templates/webhook_p4.pt
collective/webhook/locales/collective.webhook.pot
collective/webhook/locales/update.sh
collective/webhook/tests/__init__.py
collective/webhook/tests/test_webhook.py
collective/webhook/tests/profile_01/contentrules.xml
collective.webhook-0.3.0.dist-info/DESCRIPTION.rst
collective.webhook-0.3.0.dist-info/METADATA
collective.webhook-0.3.0.dist-info/RECORD
collective.webhook-0.3.0.dist-info/WHEEL
collective.webhook-0.3.0.dist-info/entry_points.txt
collective.webhook-0.3.0.dist-info/metadata.json
collective.webhook-0.3.0.dist-info/namespace_packages.txt
collective.webhook-0.3.0.dist-info/top_level.txt
