Metadata-Version: 2.0
Name: collective.webhook
Version: 0.3.0
Summary: Webhook content rule action
Home-page: https://pypi.python.org/pypi/collective.webhook
Author: Asko Soukka
Author-email: asko.soukka@iki.fi
License: GPL version 2
Keywords: Python Plone
Platform: UNKNOWN
Classifier: Environment :: Web Environment
Classifier: Framework :: Plone
Classifier: Framework :: Plone :: 4.3
Classifier: Framework :: Plone :: 5.0
Classifier: Framework :: Plone :: 5.1
Classifier: Programming Language :: Python
Classifier: Programming Language :: Python :: 2.7
Classifier: Operating System :: OS Independent
Classifier: License :: OSI Approved :: GNU General Public License v2 (GPLv2)
Requires-Dist: plone.api (>=1.8.4)
Requires-Dist: Products.GenericSetup (>=1.8.2)
Requires-Dist: requests
Requires-Dist: six
Requires-Dist: futures
Requires-Dist: setuptools
Provides-Extra: test
Requires-Dist: Pillow; extra == 'test'
Requires-Dist: plone.app.imaging; extra == 'test'
Requires-Dist: plone.app.testing; extra == 'test'
Requires-Dist: plone.testing (>=5.0.0); extra == 'test'
Requires-Dist: plone.app.contenttypes; extra == 'test'
Requires-Dist: plone.app.robotframework[debug]; extra == 'test'
